zephram/MDN.py
zephram/Recorder.py
zephram/View.py
zephram/WarmUpLR.py
zephram/__init__.py
zephram/train.py
zephram-0.0.1.dist-info/LICENSE
zephram-0.0.1.dist-info/METADATA
zephram-0.0.1.dist-info/WHEEL
zephram-0.0.1.dist-info/top_level.txt
zephram-0.0.1.dist-info/RECORD
