Metadata-Version: 2.1
Name: zephram
Version: 0.0.1
Summary: A trainer based on Pytorch
Home-page: https://github.com/ArdenteX/zephram
Author: Xavier
Author-email: Xavier <zephramxu@example.com>
Project-URL: Homepage, https://github.com/ArdenteX/zephram
Project-URL: Issues, https://github.com/ArdenteX/zephram/issues
Classifier: Programming Language :: Python :: 3
Classifier: License :: OSI Approved :: MIT License
Classifier: Operating System :: OS Independent
Requires-Python: >=3.7
License-File: LICENSE
